Classfile /c:/Users/dubey/Downloads/UJJWALPAY/frontend/public/BOOT-INF/classes/com/example/UJJWALPAY/Fingpay/controller/AepsController.class
  Last modified 18-Mar-2026; size 1398 bytes
  SHA-256 checksum 98ed5c1a2c7fd144eae7187ff49b9d3a65d9e9d048300e83ea7f9efc94670f67
  Compiled from "AepsController.java"
public class com.example.UJJWALPAY.Fingpay.controller.AepsController
  minor version: 0
  major version: 61
  flags: (0x0021) ACC_PUBLIC, ACC_SUPER
  this_class: #2                          // com/example/UJJWALPAY/Fingpay/controller/AepsController
  super_class: #14                        // java/lang/Object
  interfaces: 0, fields: 1, methods: 2, attributes: 2
Constant pool:
   #1 = Fieldref           #2.#3          // com/example/UJJWALPAY/Fingpay/controller/AepsController.service:Lcom/example/UJJWALPAY/Fingpay/service/OnboardService;
   #2 = Class              #4             // com/example/UJJWALPAY/Fingpay/controller/AepsController
   #3 = NameAndType        #5:#6          // service:Lcom/example/UJJWALPAY/Fingpay/service/OnboardService;
   #4 = Utf8               com/example/UJJWALPAY/Fingpay/controller/AepsController
   #5 = Utf8               service
   #6 = Utf8               Lcom/example/UJJWALPAY/Fingpay/service/OnboardService;
   #7 = Methodref          #8.#9          // com/example/UJJWALPAY/Fingpay/service/OnboardService.onboard:(Lcom/example/UJJWALPAY/Fingpay/dto/OnboardRequestDTO;Ljava/lang/Long;)Ljava/lang/String;
   #8 = Class              #10            // com/example/UJJWALPAY/Fingpay/service/OnboardService
   #9 = NameAndType        #11:#12        // onboard:(Lcom/example/UJJWALPAY/Fingpay/dto/OnboardRequestDTO;Ljava/lang/Long;)Ljava/lang/String;
  #10 = Utf8               com/example/UJJWALPAY/Fingpay/service/OnboardService
  #11 = Utf8               onboard
  #12 = Utf8               (Lcom/example/UJJWALPAY/Fingpay/dto/OnboardRequestDTO;Ljava/lang/Long;)Ljava/lang/String;
  #13 = Methodref          #14.#15        // java/lang/Object."<init>":()V
  #14 = Class              #16            // java/lang/Object
  #15 = NameAndType        #17:#18        // "<init>":()V
  #16 = Utf8               java/lang/Object
  #17 = Utf8               <init>
  #18 = Utf8               ()V
  #19 = Utf8               Code
  #20 = Utf8               LineNumberTable
  #21 = Utf8               LocalVariableTable
  #22 = Utf8               this
  #23 = Utf8               Lcom/example/UJJWALPAY/Fingpay/controller/AepsController;
  #24 = Utf8               dto
  #25 = Utf8               Lcom/example/UJJWALPAY/Fingpay/dto/OnboardRequestDTO;
  #26 = Utf8               userId
  #27 = Utf8               Ljava/lang/Long;
  #28 = Utf8               MethodParameters
  #29 = Utf8               RuntimeVisibleAnnotations
  #30 = Utf8               Lorg/springframework/web/bind/annotation/PostMapping;
  #31 = Utf8               value
  #32 = Utf8               /onboard
  #33 = Utf8               RuntimeVisibleParameterAnnotations
  #34 = Utf8               Lorg/springframework/web/bind/annotation/RequestBody;
  #35 = Utf8               Lorg/springframework/web/bind/annotation/RequestParam;
  #36 = Utf8               (Lcom/example/UJJWALPAY/Fingpay/service/OnboardService;)V
  #37 = Utf8               RuntimeInvisibleAnnotations
  #38 = Utf8               Llombok/Generated;
  #39 = Utf8               SourceFile
  #40 = Utf8               AepsController.java
  #41 = Utf8               Lorg/springframework/web/bind/annotation/RestController;
  #42 = Utf8               Lorg/springframework/web/bind/annotation/RequestMapping;
  #43 = Utf8               /aeps
{
  private final com.example.UJJWALPAY.Fingpay.service.OnboardService service;
    descriptor: Lcom/example/UJJWALPAY/Fingpay/service/OnboardService;
    flags: (0x0012) ACC_PRIVATE, ACC_FINAL

  public java.lang.String onboard(com.example.UJJWALPAY.Fingpay.dto.OnboardRequestDTO, java.lang.Long);
    descriptor: (Lcom/example/UJJWALPAY/Fingpay/dto/OnboardRequestDTO;Ljava/lang/Long;)Ljava/lang/String;
    flags: (0x0001) ACC_PUBLIC
    Code:
      stack=3, locals=3, args_size=3
         0: aload_0
         1: getfield      #1                  // Field service:Lcom/example/UJJWALPAY/Fingpay/service/OnboardService;
         4: aload_1
         5: aload_2
         6: invokevirtual #7                  // Method com/example/UJJWALPAY/Fingpay/service/OnboardService.onboard:(Lcom/example/UJJWALPAY/Fingpay/dto/OnboardRequestDTO;Ljava/lang/Long;)Ljava/lang/String;
         9: areturn
      LineNumberTable:
        line 19: 0
      LocalVariableTable:
        Start  Length  Slot  Name   Signature
            0      10     0  this   Lcom/example/UJJWALPAY/Fingpay/controller/AepsController;
            0      10     1   dto   Lcom/example/UJJWALPAY/Fingpay/dto/OnboardRequestDTO;
            0      10     2 userId   Ljava/lang/Long;
    MethodParameters:
      Name                           Flags
      dto
      userId
    RuntimeVisibleAnnotations:
      0: #30(#31=[s#32])
        org.springframework.web.bind.annotation.PostMapping(
          value=["/onboard"]
        )
    RuntimeVisibleParameterAnnotations:
      parameter 0:
        0: #34()
          org.springframework.web.bind.annotation.RequestBody
      parameter 1:
        0: #35()
          org.springframework.web.bind.annotation.RequestParam

  public com.example.UJJWALPAY.Fingpay.controller.AepsController(com.example.UJJWALPAY.Fingpay.service.OnboardService);
    descriptor: (Lcom/example/UJJWALPAY/Fingpay/service/OnboardService;)V
    flags: (0x0001) ACC_PUBLIC
    Code:
      stack=2, locals=2, args_size=2
         0: aload_0
         1: invokespecial #13                 // Method java/lang/Object."<init>":()V
         4: aload_0
         5: aload_1
         6: putfield      #1                  // Field service:Lcom/example/UJJWALPAY/Fingpay/service/OnboardService;
         9: return
      LineNumberTable:
        line 10: 0
      LocalVariableTable:
        Start  Length  Slot  Name   Signature
            0      10     0  this   Lcom/example/UJJWALPAY/Fingpay/controller/AepsController;
            0      10     1 service   Lcom/example/UJJWALPAY/Fingpay/service/OnboardService;
    MethodParameters:
      Name                           Flags
      service                        final
    RuntimeInvisibleAnnotations:
      0: #38()
        lombok.Generated
}
SourceFile: "AepsController.java"
RuntimeVisibleAnnotations:
  0: #41()
    org.springframework.web.bind.annotation.RestController
  1: #42(#31=[s#43])
    org.springframework.web.bind.annotation.RequestMapping(
      value=["/aeps"]
    )
